tehzor/__init__.py
tehzor/api.py
tehzor/constants.py
tehzor/models.py
tehzor/models/__init__.py
tehzor/models/attachment.py
tehzor/models/base.py
tehzor/models/category.py
tehzor/models/construction.py
tehzor/models/health_check.py
tehzor/models/owner.py
tehzor/models/problem.py
tehzor/models/space.py
tehzor/models/space_decoration.py
tehzor/models/space_meters.py
tehzor/models/status.py
tehzor/models/user.py
tehzor/models/warranty_claims.py
tehzor/models/workacceptances.py
tehzor-0.1.3.dist-info/LICENSE.txt
tehzor-0.1.3.dist-info/METADATA
tehzor-0.1.3.dist-info/WHEEL
tehzor-0.1.3.dist-info/top_level.txt
tehzor-0.1.3.dist-info/RECORD
