Metadata-Version: 2.1
Name: tehzor
Version: 0.1.3
Summary: A Python API wrapper for Tehzor API
Home-page: https://github.com/gritsyuk/tehzor
Download-URL: https://github.com/gritsyuk/tehzor/archive/refs/heads/develop.zip
Author: Igor Gritsyuk
Author-email: gritsyuk.igor@gmail.com
Project-URL: GitHub, https://github.com/gritsyuk/tehzor
Keywords: tehzor api tehzorapi construction supervision operation inspections constarctionsite building management
Classifier: Programming Language :: Python :: 3
Classifier: License :: OSI Approved :: MIT License
Classifier: Operating System :: OS Independent
Requires-Python: >=3.6
License-File: LICENSE.txt
Requires-Dist: aiohttp >=3.9.3
Requires-Dist: pydantic[email] >=2.6.4
